branalysis/__init__.py
branalysis/agrupador.py
branalysis/colorizador.py
branalysis/matriz_politica.py
branalysis/plenario.py
branalysis/db/__init__.py
branalysis/db/camara.py
branalysis/db/camara_parlamentares.py
branalysis/db/camara_proposicoes.py
branalysis/db/camara_votos.py
branalysis/db/model.py
branalysis/db/senado.py
branalysis/db/senado_parlamentares.py
branalysis/db/utils.py
branalysis-1.0.12.dist-info/LICENSE
branalysis-1.0.12.dist-info/METADATA
branalysis-1.0.12.dist-info/WHEEL
branalysis-1.0.12.dist-info/top_level.txt
branalysis-1.0.12.dist-info/RECORD
