Metadata-Version: 2.1
Name: branalysis
Version: 1.0.12
Summary: Coleta e facilita a análise de votações nominais do Congresso Nacional
Home-page: https://github.com/mateuskreuch/branalysis
Author: Mateus Arns Kreuch
Author-email: mateus.kreuch@grad.ufsc.br
Classifier: Programming Language :: Python :: 3
Classifier: Operating System :: OS Independent
Classifier: Topic :: Scientific/Engineering :: Information Analysis
Classifier: Topic :: Scientific/Engineering :: Visualization
Classifier: Topic :: Sociology
Classifier: Intended Audience :: Developers
Classifier: Intended Audience :: Science/Research
Classifier: Natural Language :: Portuguese (Brazilian)
Requires-Python: >=3.9
License-File: LICENSE
Requires-Dist: numpy
Requires-Dist: peewee
Requires-Dist: Requests
